trustpilot_json_logging/__init__.py
trustpilot_json_logging/jsonlogger.py
trustpilot_json_logging-1.0.12.dist-info/LICENSE
trustpilot_json_logging-1.0.12.dist-info/WHEEL
trustpilot_json_logging-1.0.12.dist-info/METADATA
trustpilot_json_logging-1.0.12.dist-info/RECORD
