Metadata-Version: 2.1
Name: trustpilot-json-logging
Version: 1.0.12
Summary: Opinionated JSON logger
Home-page: https://github.com/trustpilot/python-logging
License: BSD-2-Clause
Author: sloev
Author-email: johanned.valbjorn@gmail.com
Requires-Python: >=3.6,<4.0
Classifier: Development Status :: 5 - Production/Stable
Classifier: Intended Audience :: Developers
Classifier: License :: OSI Approved :: BSD License
Classifier: Natural Language :: English
Classifier: Programming Language :: Python :: 3
Classifier: Programming Language :: Python :: 3.6
Classifier: Programming Language :: Python :: 3.7
Classifier: Programming Language :: Python :: 3.8
Project-URL: Repository, https://github.com/trustpilot/python-logging
